{
  "_cached_at": "2026-03-10T20:58:35.602784",
  "data": {
    "r": 0,
    "subject": {
      "episodes_count": "",
      "star": 4.0,
      "blacklisted": "available",
      "title": "东北警察故事3‎ (2026)",
      "url": "https://movie.douban.com/subject/36977669/",
      "collection_status": "",
      "rate": "7.6",
      "short_comment": {
        "content": "李红旗对战秦姐夫妇全片最佳！封闭空间、亡命暴徒、近身肉搏要素拉满，不管是绞杀还是冲撞每一招都是致死的力量，节奏和光影有种黑色电影的vibe，看得好爽。",
        "author": "豆瓣天后董小姐"
      },
      "is_tv": false,
      "subtype": "Movie",
      "directors": [
        "杨秉佳"
      ],
      "actors": [
        "谢苗",
        "林晓杰",
        "崔志佳",
        "黄米依",
        "伍允龙",
        "马千壹",
        "张磊",
        "冯瑶",
        "唐鉴军",
        "田娃"
      ],
      "duration": "100分钟",
      "region": "中国大陆",
      "playable": true,
      "id": "36977669",
      "types": [
        "喜剧",
        "动作",
        "犯罪"
      ],
      "release_year": "2026"
    }
  }
}